RanDepict/__init__.py
RanDepict/augmentations.py
RanDepict/cdk_functionalities.py
RanDepict/config.py
RanDepict/depiction_feature_ranges.py
RanDepict/import augmentations.py
RanDepict/indigo_functionalities.py
RanDepict/pikachu_functionalities.py
RanDepict/randepict.py
RanDepict/random_markush_structure_generator.py
RanDepict/rdkit_functionalities.py
RanDepict/assets/CDK_fingerprints.npz
RanDepict/assets/Indigo_fingerprints.npz
RanDepict/assets/PIKAChU_fingerprints.npz
RanDepict/assets/RDKit_fingerprints.npz
RanDepict/assets/augmentation_fingerprints.npz
RanDepict/assets/cdk_alt_superatom_abbreviations.smi
RanDepict/assets/cdk_superatom_abbreviations.smi
RanDepict/assets/rdkit_alternative_superatom_abbreviations.txt
RanDepict/assets/superatom.txt
RanDepict/assets/arrow_images/curved_arrows/02_curved_arrow_one_head_01.png
RanDepict/assets/arrow_images/curved_arrows/02_curved_arrow_one_head_02.png
RanDepict/assets/arrow_images/curved_arrows/02_curved_arrow_one_head_03.png
RanDepict/assets/arrow_images/curved_arrows/02_curved_arrow_one_head_04.png
RanDepict/assets/arrow_images/curved_arrows/02_curved_arrow_one_head_05.png
RanDepict/assets/arrow_images/curved_arrows/02_curved_arrow_one_head_06.png
RanDepict/assets/arrow_images/curved_arrows/02_curved_arrow_one_head_07.png
RanDepict/assets/arrow_images/curved_arrows/02_curved_arrow_one_head_08.png
RanDepict/assets/arrow_images/curved_arrows/02_curved_arrow_one_head_09.png
RanDepict/assets/arrow_images/curved_arrows/02_curved_arrow_two_heads_01.png
RanDepict/assets/arrow_images/curved_arrows/02_curved_arrow_two_heads_02.png
RanDepict/assets/arrow_images/curved_arrows/02_curved_arrow_two_heads_03.png
RanDepict/assets/arrow_images/curved_arrows/02_curved_arrow_two_heads_04.png
RanDepict/assets/arrow_images/straight_arrows/01_left_right_eq_arrow_1.png
RanDepict/assets/arrow_images/straight_arrows/01_left_right_eq_arrow_2.png
RanDepict/assets/arrow_images/straight_arrows/01_left_right_eq_arrow_3.png
RanDepict-1.3.0.dist-info/LICENSE
RanDepict-1.3.0.dist-info/METADATA
RanDepict-1.3.0.dist-info/WHEEL
RanDepict-1.3.0.dist-info/top_level.txt
RanDepict-1.3.0.dist-info/RECORD
