Metadata-Version: 2.1
Name: RanDepict
Version: 1.3.0
Summary: RanDepict is an easy-to-use utility to generate a big variety of chemical structure depictions (random depiction styles and image augmentations).
Home-page: https://github.com/OBrink/RanDepict
Author: Otto Brinkhaus
Author-email: otto.brinkhaus@uni-jena.de, kohulan.rajan@uni-jena.de
Maintainer: Otto Brinkhaus, Kohulan Rajan
Maintainer-email: otto.brinkhaus@uni-jena.de, kohulan.rajan@uni-jena.de
License: MIT
Classifier: Programming Language :: Python :: 3
Classifier: Programming Language :: Python :: 3.7
Classifier: Programming Language :: Python :: 3.8
Classifier: Programming Language :: Python :: 3.9
Classifier: Programming Language :: Python :: 3.10
Classifier: Programming Language :: Python :: 3 :: Only
Classifier: License :: OSI Approved :: MIT License
Classifier: Operating System :: OS Independent
Requires-Python: >=3.7
License-File: LICENSE
Requires-Dist: numpy >=1.19
Requires-Dist: imgaug
Requires-Dist: scikit-image
Requires-Dist: epam.indigo
Requires-Dist: jpype1
Requires-Dist: ipyplot
Requires-Dist: rdkit
Requires-Dist: imagecorruptions
Requires-Dist: pillow >=8.2.0
Requires-Dist: pikachu-chem >=1.0.7
Requires-Dist: omegaconf
Requires-Dist: typing-extensions ; python_version < "3.8"
Provides-Extra: dev
Requires-Dist: tox ; extra == 'dev'
Requires-Dist: pytest ; extra == 'dev'
